incuna_request_logging-0.1.0.dist-info/top_level.txt
incuna_request_logging-0.1.0.dist-info/DESCRIPTION.rst
incuna_request_logging-0.1.0.dist-info/RECORD
incuna_request_logging-0.1.0.dist-info/metadata.json
incuna_request_logging-0.1.0.dist-info/METADATA
incuna_request_logging-0.1.0.dist-info/WHEEL
logger/models.py
logger/__init__.py
logger/middleware.py
logger/admin.py
