Metadata-Version: 2.0
Name: incuna-request-logging
Version: 0.1.0
Summary: Django request logging
Home-page: https://github.com/incuna/incuna-request-logging
Author: Incuna
Author-email: admin@incuna.com
License: BSD
Platform: UNKNOWN
Classifier: Development Status :: 3 - Alpha
Classifier: Intended Audience :: Developers
Classifier: Topic :: Communications
Classifier: License :: OSI Approved :: BSD License
Classifier: Programming Language :: Python :: 3
Classifier: Programming Language :: Python :: 3 :: Only
Classifier: Programming Language :: Python :: 3.4
